reaction/__init__.py
reaction/admin.py
reaction/apps.py
reaction/models.py
reaction/settings.py
reaction/tests.py
reaction/urls.py
reaction/views.py
reaction/migrations/0001_initial.py
reaction/migrations/0002_config.py
reaction/migrations/__init__.py
reaction/static/reaction/css/reaction.css
reaction/static/reaction/css/reaction.min.css
reaction/static/reaction/js/reaction.js
reaction/static/reaction/js/reaction.min.js
reaction/static/reaction/tailwindcss/style.css
reaction/static/reaction/tailwindcss/tailwind.config.js
reaction/templates/reaction/reaction/reaction.html
reaction/templates/reaction/reaction/reaction_form.html
reaction/templates/reaction/utils/IMPORTS.html
reaction/templates/reaction/utils/SCRIPTS.html
reaction/templatetags/__init__.py
reaction/templatetags/reaction_tags.py
django_reaction_system-1.1.1.dist-info/LICENSE
django_reaction_system-1.1.1.dist-info/METADATA
django_reaction_system-1.1.1.dist-info/WHEEL
django_reaction_system-1.1.1.dist-info/top_level.txt
django_reaction_system-1.1.1.dist-info/RECORD
