Metadata-Version: 2.1
Name: django-reaction-system
Version: 1.1.1
Summary: Django reaction System, It can be associated with any given model.
Home-page: https://github.com/mahyar-amiri/django-reaction-system
Author: Mahyar Amiri
Author-email: mmaahhyyaarr@gmail.com
License: MIT
Project-URL: Documentation, https://github.com/mahyar-amiri/django-reaction-system/README.md
Project-URL: Source Code, https://github.com/mahyar-amiri/django-reaction-system
Keywords: django reaction reaction-system django-reaction reactions reactions-system django-reactions ajax
License-File: LICENSE
Requires-Dist: django
Requires-Dist: pillow
Provides-Extra: markdown
Requires-Dist: markdown ; extra == 'markdown'
